anaconda_assistant/__init__.py
anaconda_assistant/_version.py
anaconda_assistant/api_client.py
anaconda_assistant/config.py
anaconda_assistant/core.py
anaconda_assistant/exceptions.py
anaconda_assistant/py.typed
anaconda_assistant/integrations/Anaconda_Logo.png
anaconda_assistant/integrations/__init__.py
anaconda_assistant/integrations/ell.py
anaconda_assistant/integrations/langchain.py
anaconda_assistant/integrations/llama_index.py
anaconda_assistant/integrations/llm.py
anaconda_assistant/integrations/pandasai.py
anaconda_assistant/integrations/panel.py
anaconda_assistant_sdk-0.5.2.dist-info/METADATA
anaconda_assistant_sdk-0.5.2.dist-info/WHEEL
anaconda_assistant_sdk-0.5.2.dist-info/entry_points.txt
anaconda_assistant_sdk-0.5.2.dist-info/licenses/LICENSE
anaconda_assistant_sdk-0.5.2.dist-info/RECORD
