Metadata-Version: 2.4
Name: anaconda-assistant-sdk
Version: 0.5.2
Summary: The Anaconda Assistant Python client
License: BSD-3-Clause
License-File: LICENSE
Requires-Python: >=3.9
Requires-Dist: anaconda-auth>=0.8
Requires-Dist: anaconda-cli-base>=0.5
Requires-Dist: pydantic
Provides-Extra: dev
Requires-Dist: mypy; extra == 'dev'
Requires-Dist: pytest; extra == 'dev'
Requires-Dist: pytest-cov; extra == 'dev'
Requires-Dist: pytest-mock; extra == 'dev'
Requires-Dist: responses; extra == 'dev'
Requires-Dist: tox; extra == 'dev'
Requires-Dist: types-requests; extra == 'dev'
Provides-Extra: ell
Requires-Dist: ell-ai; extra == 'ell'
Provides-Extra: langchain
Requires-Dist: langchain-core>=0.3; extra == 'langchain'
Provides-Extra: llama-index
Requires-Dist: llama-index-core; extra == 'llama-index'
Provides-Extra: llm
Requires-Dist: llm>=0.22; extra == 'llm'
Provides-Extra: pandasai
Requires-Dist: pandasai>=2.4; extra == 'pandasai'
Provides-Extra: panel
Requires-Dist: panel>=1.6; extra == 'panel'
Provides-Extra: publish
Requires-Dist: build; extra == 'publish'
Requires-Dist: twine; extra == 'publish'
Requires-Dist: wheel; extra == 'publish'
